<?xml version='1.0' encoding='UTF-8'?>
<commonRoad commonRoadVersion="2020a" benchmarkID="ZAM_CutIn-1_1_T-1" date="2026-07-06" author="nanoplan" affiliation="nanoplan (https://github.com/BenGravell/nanoplan)" source="synthetic (tools/generate_diverse_scenarios.py)" timeStepSize="0.1">
 <location>
  <geoNameId>-999</geoNameId>
  <gpsLatitude>999</gpsLatitude>
  <gpsLongitude>999</gpsLongitude>
 </location>
 <scenarioTags>
  <urban />
  <multi_lane />
  <no_oncoming_traffic />
  <parallel_lanes />
  <simulated />
 </scenarioTags>
 <lanelet id="100">
  <leftBound>
   <point>
    <x>-50.0</x>
    <y>2.0</y>
   </point>
   <point>
    <x>-45.0</x>
    <y>2.0</y>
   </point>
   <point>
    <x>-40.0</x>
    <y>2.0</y>
   </point>
   <point>
    <x>-35.0</x>
    <y>2.0</y>
   </point>
   <point>
    <x>-30.0</x>
    <y>2.0</y>
   </point>
   <point>
    <x>-25.0</x>
    <y>2.0</y>
   </point>
   <point>
    <x>-20.0</x>
    <y>2.0</y>
   </point>
   <point>
    <x>-15.0</x>
    <y>2.0</y>
   </point>
   <point>
    <x>-10.0</x>
    <y>2.0</y>
   </point>
   <point>
    <x>-5.0</x>
    <y>2.0</y>
   </point>
   <point>
    <x>0.0</x>
    <y>2.0</y>
   </point>
   <point>
    <x>5.0</x>
    <y>2.0</y>
   </point>
   <point>
    <x>10.0</x>
    <y>2.0</y>
   </point>
   <point>
    <x>15.0</x>
    <y>2.0</y>
   </point>
   <point>
    <x>20.0</x>
    <y>2.0</y>
   </point>
   <point>
    <x>25.0</x>
    <y>2.0</y>
   </point>
   <point>
    <x>30.0</x>
    <y>2.0</y>
   </point>
   <point>
    <x>35.0</x>
    <y>2.0</y>
   </point>
   <point>
    <x>40.0</x>
    <y>2.0</y>
   </point>
   <point>
    <x>45.0</x>
    <y>2.0</y>
   </point>
   <point>
    <x>50.0</x>
    <y>2.0</y>
   </point>
   <point>
    <x>55.0</x>
    <y>2.0</y>
   </point>
   <point>
    <x>60.0</x>
    <y>2.0</y>
   </point>
   <point>
    <x>65.0</x>
    <y>2.0</y>
   </point>
   <point>
    <x>70.0</x>
    <y>2.0</y>
   </point>
   <point>
    <x>75.0</x>
    <y>2.0</y>
   </point>
   <point>
    <x>80.0</x>
    <y>2.0</y>
   </point>
   <point>
    <x>85.0</x>
    <y>2.0</y>
   </point>
   <point>
    <x>90.0</x>
    <y>2.0</y>
   </point>
   <point>
    <x>95.0</x>
    <y>2.0</y>
   </point>
   <point>
    <x>100.0</x>
    <y>2.0</y>
   </point>
   <point>
    <x>105.0</x>
    <y>2.0</y>
   </point>
   <point>
    <x>110.0</x>
    <y>2.0</y>
   </point>
   <point>
    <x>115.0</x>
    <y>2.0</y>
   </point>
   <point>
    <x>120.0</x>
    <y>2.0</y>
   </point>
   <point>
    <x>125.0</x>
    <y>2.0</y>
   </point>
   <point>
    <x>130.0</x>
    <y>2.0</y>
   </point>
   <point>
    <x>135.0</x>
    <y>2.0</y>
   </point>
   <point>
    <x>140.0</x>
    <y>2.0</y>
   </point>
   <point>
    <x>145.0</x>
    <y>2.0</y>
   </point>
   <point>
    <x>150.0</x>
    <y>2.0</y>
   </point>
   <point>
    <x>155.0</x>
    <y>2.0</y>
   </point>
   <point>
    <x>160.0</x>
    <y>2.0</y>
   </point>
   <point>
    <x>165.0</x>
    <y>2.0</y>
   </point>
   <point>
    <x>170.0</x>
    <y>2.0</y>
   </point>
   <point>
    <x>175.0</x>
    <y>2.0</y>
   </point>
   <point>
    <x>180.0</x>
    <y>2.0</y>
   </point>
   <point>
    <x>185.0</x>
    <y>2.0</y>
   </point>
   <point>
    <x>190.0</x>
    <y>2.0</y>
   </point>
   <point>
    <x>195.0</x>
    <y>2.0</y>
   </point>
   <point>
    <x>200.0</x>
    <y>2.0</y>
   </point>
   <point>
    <x>205.0</x>
    <y>2.0</y>
   </point>
   <point>
    <x>210.0</x>
    <y>2.0</y>
   </point>
   <point>
    <x>215.0</x>
    <y>2.0</y>
   </point>
   <point>
    <x>220.0</x>
    <y>2.0</y>
   </point>
   <point>
    <x>225.0</x>
    <y>2.0</y>
   </point>
   <point>
    <x>230.0</x>
    <y>2.0</y>
   </point>
   <point>
    <x>235.0</x>
    <y>2.0</y>
   </point>
   <point>
    <x>240.0</x>
    <y>2.0</y>
   </point>
   <point>
    <x>245.0</x>
    <y>2.0</y>
   </point>
   <point>
    <x>250.0</x>
    <y>2.0</y>
   </point>
   <point>
    <x>255.0</x>
    <y>2.0</y>
   </point>
   <point>
    <x>260.0</x>
    <y>2.0</y>
   </point>
   <point>
    <x>265.0</x>
    <y>2.0</y>
   </point>
   <point>
    <x>270.0</x>
    <y>2.0</y>
   </point>
   <point>
    <x>275.0</x>
    <y>2.0</y>
   </point>
   <point>
    <x>280.0</x>
    <y>2.0</y>
   </point>
   <point>
    <x>285.0</x>
    <y>2.0</y>
   </point>
   <point>
    <x>290.0</x>
    <y>2.0</y>
   </point>
   <point>
    <x>295.0</x>
    <y>2.0</y>
   </point>
   <point>
    <x>300.0</x>
    <y>2.0</y>
   </point>
   <point>
    <x>305.0</x>
    <y>2.0</y>
   </point>
   <point>
    <x>310.0</x>
    <y>2.0</y>
   </point>
   <point>
    <x>315.0</x>
    <y>2.0</y>
   </point>
   <point>
    <x>320.0</x>
    <y>2.0</y>
   </point>
   <point>
    <x>325.0</x>
    <y>2.0</y>
   </point>
   <point>
    <x>330.0</x>
    <y>2.0</y>
   </point>
   <point>
    <x>335.0</x>
    <y>2.0</y>
   </point>
   <point>
    <x>340.0</x>
    <y>2.0</y>
   </point>
   <point>
    <x>345.0</x>
    <y>2.0</y>
   </point>
   <point>
    <x>350.0</x>
    <y>2.0</y>
   </point>
   <point>
    <x>355.0</x>
    <y>2.0</y>
   </point>
   <point>
    <x>360.0</x>
    <y>2.0</y>
   </point>
   <point>
    <x>365.0</x>
    <y>2.0</y>
   </point>
   <point>
    <x>370.0</x>
    <y>2.0</y>
   </point>
   <point>
    <x>375.0</x>
    <y>2.0</y>
   </point>
   <point>
    <x>380.0</x>
    <y>2.0</y>
   </point>
   <point>
    <x>385.0</x>
    <y>2.0</y>
   </point>
   <point>
    <x>390.0</x>
    <y>2.0</y>
   </point>
   <point>
    <x>395.0</x>
    <y>2.0</y>
   </point>
   <point>
    <x>400.0</x>
    <y>2.0</y>
   </point>
   <lineMarking>dashed</lineMarking>
  </leftBound>
  <rightBound>
   <point>
    <x>-50.0</x>
    <y>-2.0</y>
   </point>
   <point>
    <x>-45.0</x>
    <y>-2.0</y>
   </point>
   <point>
    <x>-40.0</x>
    <y>-2.0</y>
   </point>
   <point>
    <x>-35.0</x>
    <y>-2.0</y>
   </point>
   <point>
    <x>-30.0</x>
    <y>-2.0</y>
   </point>
   <point>
    <x>-25.0</x>
    <y>-2.0</y>
   </point>
   <point>
    <x>-20.0</x>
    <y>-2.0</y>
   </point>
   <point>
    <x>-15.0</x>
    <y>-2.0</y>
   </point>
   <point>
    <x>-10.0</x>
    <y>-2.0</y>
   </point>
   <point>
    <x>-5.0</x>
    <y>-2.0</y>
   </point>
   <point>
    <x>0.0</x>
    <y>-2.0</y>
   </point>
   <point>
    <x>5.0</x>
    <y>-2.0</y>
   </point>
   <point>
    <x>10.0</x>
    <y>-2.0</y>
   </point>
   <point>
    <x>15.0</x>
    <y>-2.0</y>
   </point>
   <point>
    <x>20.0</x>
    <y>-2.0</y>
   </point>
   <point>
    <x>25.0</x>
    <y>-2.0</y>
   </point>
   <point>
    <x>30.0</x>
    <y>-2.0</y>
   </point>
   <point>
    <x>35.0</x>
    <y>-2.0</y>
   </point>
   <point>
    <x>40.0</x>
    <y>-2.0</y>
   </point>
   <point>
    <x>45.0</x>
    <y>-2.0</y>
   </point>
   <point>
    <x>50.0</x>
    <y>-2.0</y>
   </point>
   <point>
    <x>55.0</x>
    <y>-2.0</y>
   </point>
   <point>
    <x>60.0</x>
    <y>-2.0</y>
   </point>
   <point>
    <x>65.0</x>
    <y>-2.0</y>
   </point>
   <point>
    <x>70.0</x>
    <y>-2.0</y>
   </point>
   <point>
    <x>75.0</x>
    <y>-2.0</y>
   </point>
   <point>
    <x>80.0</x>
    <y>-2.0</y>
   </point>
   <point>
    <x>85.0</x>
    <y>-2.0</y>
   </point>
   <point>
    <x>90.0</x>
    <y>-2.0</y>
   </point>
   <point>
    <x>95.0</x>
    <y>-2.0</y>
   </point>
   <point>
    <x>100.0</x>
    <y>-2.0</y>
   </point>
   <point>
    <x>105.0</x>
    <y>-2.0</y>
   </point>
   <point>
    <x>110.0</x>
    <y>-2.0</y>
   </point>
   <point>
    <x>115.0</x>
    <y>-2.0</y>
   </point>
   <point>
    <x>120.0</x>
    <y>-2.0</y>
   </point>
   <point>
    <x>125.0</x>
    <y>-2.0</y>
   </point>
   <point>
    <x>130.0</x>
    <y>-2.0</y>
   </point>
   <point>
    <x>135.0</x>
    <y>-2.0</y>
   </point>
   <point>
    <x>140.0</x>
    <y>-2.0</y>
   </point>
   <point>
    <x>145.0</x>
    <y>-2.0</y>
   </point>
   <point>
    <x>150.0</x>
    <y>-2.0</y>
   </point>
   <point>
    <x>155.0</x>
    <y>-2.0</y>
   </point>
   <point>
    <x>160.0</x>
    <y>-2.0</y>
   </point>
   <point>
    <x>165.0</x>
    <y>-2.0</y>
   </point>
   <point>
    <x>170.0</x>
    <y>-2.0</y>
   </point>
   <point>
    <x>175.0</x>
    <y>-2.0</y>
   </point>
   <point>
    <x>180.0</x>
    <y>-2.0</y>
   </point>
   <point>
    <x>185.0</x>
    <y>-2.0</y>
   </point>
   <point>
    <x>190.0</x>
    <y>-2.0</y>
   </point>
   <point>
    <x>195.0</x>
    <y>-2.0</y>
   </point>
   <point>
    <x>200.0</x>
    <y>-2.0</y>
   </point>
   <point>
    <x>205.0</x>
    <y>-2.0</y>
   </point>
   <point>
    <x>210.0</x>
    <y>-2.0</y>
   </point>
   <point>
    <x>215.0</x>
    <y>-2.0</y>
   </point>
   <point>
    <x>220.0</x>
    <y>-2.0</y>
   </point>
   <point>
    <x>225.0</x>
    <y>-2.0</y>
   </point>
   <point>
    <x>230.0</x>
    <y>-2.0</y>
   </point>
   <point>
    <x>235.0</x>
    <y>-2.0</y>
   </point>
   <point>
    <x>240.0</x>
    <y>-2.0</y>
   </point>
   <point>
    <x>245.0</x>
    <y>-2.0</y>
   </point>
   <point>
    <x>250.0</x>
    <y>-2.0</y>
   </point>
   <point>
    <x>255.0</x>
    <y>-2.0</y>
   </point>
   <point>
    <x>260.0</x>
    <y>-2.0</y>
   </point>
   <point>
    <x>265.0</x>
    <y>-2.0</y>
   </point>
   <point>
    <x>270.0</x>
    <y>-2.0</y>
   </point>
   <point>
    <x>275.0</x>
    <y>-2.0</y>
   </point>
   <point>
    <x>280.0</x>
    <y>-2.0</y>
   </point>
   <point>
    <x>285.0</x>
    <y>-2.0</y>
   </point>
   <point>
    <x>290.0</x>
    <y>-2.0</y>
   </point>
   <point>
    <x>295.0</x>
    <y>-2.0</y>
   </point>
   <point>
    <x>300.0</x>
    <y>-2.0</y>
   </point>
   <point>
    <x>305.0</x>
    <y>-2.0</y>
   </point>
   <point>
    <x>310.0</x>
    <y>-2.0</y>
   </point>
   <point>
    <x>315.0</x>
    <y>-2.0</y>
   </point>
   <point>
    <x>320.0</x>
    <y>-2.0</y>
   </point>
   <point>
    <x>325.0</x>
    <y>-2.0</y>
   </point>
   <point>
    <x>330.0</x>
    <y>-2.0</y>
   </point>
   <point>
    <x>335.0</x>
    <y>-2.0</y>
   </point>
   <point>
    <x>340.0</x>
    <y>-2.0</y>
   </point>
   <point>
    <x>345.0</x>
    <y>-2.0</y>
   </point>
   <point>
    <x>350.0</x>
    <y>-2.0</y>
   </point>
   <point>
    <x>355.0</x>
    <y>-2.0</y>
   </point>
   <point>
    <x>360.0</x>
    <y>-2.0</y>
   </point>
   <point>
    <x>365.0</x>
    <y>-2.0</y>
   </point>
   <point>
    <x>370.0</x>
    <y>-2.0</y>
   </point>
   <point>
    <x>375.0</x>
    <y>-2.0</y>
   </point>
   <point>
    <x>380.0</x>
    <y>-2.0</y>
   </point>
   <point>
    <x>385.0</x>
    <y>-2.0</y>
   </point>
   <point>
    <x>390.0</x>
    <y>-2.0</y>
   </point>
   <point>
    <x>395.0</x>
    <y>-2.0</y>
   </point>
   <point>
    <x>400.0</x>
    <y>-2.0</y>
   </point>
   <lineMarking>solid</lineMarking>
  </rightBound>
  <adjacentLeft ref="101" drivingDir="same" />
  <laneletType>urban</laneletType>
 </lanelet>
 <lanelet id="101">
  <leftBound>
   <point>
    <x>-50.0</x>
    <y>5.5</y>
   </point>
   <point>
    <x>-45.0</x>
    <y>5.5</y>
   </point>
   <point>
    <x>-40.0</x>
    <y>5.5</y>
   </point>
   <point>
    <x>-35.0</x>
    <y>5.5</y>
   </point>
   <point>
    <x>-30.0</x>
    <y>5.5</y>
   </point>
   <point>
    <x>-25.0</x>
    <y>5.5</y>
   </point>
   <point>
    <x>-20.0</x>
    <y>5.5</y>
   </point>
   <point>
    <x>-15.0</x>
    <y>5.5</y>
   </point>
   <point>
    <x>-10.0</x>
    <y>5.5</y>
   </point>
   <point>
    <x>-5.0</x>
    <y>5.5</y>
   </point>
   <point>
    <x>0.0</x>
    <y>5.5</y>
   </point>
   <point>
    <x>5.0</x>
    <y>5.5</y>
   </point>
   <point>
    <x>10.0</x>
    <y>5.5</y>
   </point>
   <point>
    <x>15.0</x>
    <y>5.5</y>
   </point>
   <point>
    <x>20.0</x>
    <y>5.5</y>
   </point>
   <point>
    <x>25.0</x>
    <y>5.5</y>
   </point>
   <point>
    <x>30.0</x>
    <y>5.5</y>
   </point>
   <point>
    <x>35.0</x>
    <y>5.5</y>
   </point>
   <point>
    <x>40.0</x>
    <y>5.5</y>
   </point>
   <point>
    <x>45.0</x>
    <y>5.5</y>
   </point>
   <point>
    <x>50.0</x>
    <y>5.5</y>
   </point>
   <point>
    <x>55.0</x>
    <y>5.5</y>
   </point>
   <point>
    <x>60.0</x>
    <y>5.5</y>
   </point>
   <point>
    <x>65.0</x>
    <y>5.5</y>
   </point>
   <point>
    <x>70.0</x>
    <y>5.5</y>
   </point>
   <point>
    <x>75.0</x>
    <y>5.5</y>
   </point>
   <point>
    <x>80.0</x>
    <y>5.5</y>
   </point>
   <point>
    <x>85.0</x>
    <y>5.5</y>
   </point>
   <point>
    <x>90.0</x>
    <y>5.5</y>
   </point>
   <point>
    <x>95.0</x>
    <y>5.5</y>
   </point>
   <point>
    <x>100.0</x>
    <y>5.5</y>
   </point>
   <point>
    <x>105.0</x>
    <y>5.5</y>
   </point>
   <point>
    <x>110.0</x>
    <y>5.5</y>
   </point>
   <point>
    <x>115.0</x>
    <y>5.5</y>
   </point>
   <point>
    <x>120.0</x>
    <y>5.5</y>
   </point>
   <point>
    <x>125.0</x>
    <y>5.5</y>
   </point>
   <point>
    <x>130.0</x>
    <y>5.5</y>
   </point>
   <point>
    <x>135.0</x>
    <y>5.5</y>
   </point>
   <point>
    <x>140.0</x>
    <y>5.5</y>
   </point>
   <point>
    <x>145.0</x>
    <y>5.5</y>
   </point>
   <point>
    <x>150.0</x>
    <y>5.5</y>
   </point>
   <point>
    <x>155.0</x>
    <y>5.5</y>
   </point>
   <point>
    <x>160.0</x>
    <y>5.5</y>
   </point>
   <point>
    <x>165.0</x>
    <y>5.5</y>
   </point>
   <point>
    <x>170.0</x>
    <y>5.5</y>
   </point>
   <point>
    <x>175.0</x>
    <y>5.5</y>
   </point>
   <point>
    <x>180.0</x>
    <y>5.5</y>
   </point>
   <point>
    <x>185.0</x>
    <y>5.5</y>
   </point>
   <point>
    <x>190.0</x>
    <y>5.5</y>
   </point>
   <point>
    <x>195.0</x>
    <y>5.5</y>
   </point>
   <point>
    <x>200.0</x>
    <y>5.5</y>
   </point>
   <point>
    <x>205.0</x>
    <y>5.5</y>
   </point>
   <point>
    <x>210.0</x>
    <y>5.5</y>
   </point>
   <point>
    <x>215.0</x>
    <y>5.5</y>
   </point>
   <point>
    <x>220.0</x>
    <y>5.5</y>
   </point>
   <point>
    <x>225.0</x>
    <y>5.5</y>
   </point>
   <point>
    <x>230.0</x>
    <y>5.5</y>
   </point>
   <point>
    <x>235.0</x>
    <y>5.5</y>
   </point>
   <point>
    <x>240.0</x>
    <y>5.5</y>
   </point>
   <point>
    <x>245.0</x>
    <y>5.5</y>
   </point>
   <point>
    <x>250.0</x>
    <y>5.5</y>
   </point>
   <point>
    <x>255.0</x>
    <y>5.5</y>
   </point>
   <point>
    <x>260.0</x>
    <y>5.5</y>
   </point>
   <point>
    <x>265.0</x>
    <y>5.5</y>
   </point>
   <point>
    <x>270.0</x>
    <y>5.5</y>
   </point>
   <point>
    <x>275.0</x>
    <y>5.5</y>
   </point>
   <point>
    <x>280.0</x>
    <y>5.5</y>
   </point>
   <point>
    <x>285.0</x>
    <y>5.5</y>
   </point>
   <point>
    <x>290.0</x>
    <y>5.5</y>
   </point>
   <point>
    <x>295.0</x>
    <y>5.5</y>
   </point>
   <point>
    <x>300.0</x>
    <y>5.5</y>
   </point>
   <point>
    <x>305.0</x>
    <y>5.5</y>
   </point>
   <point>
    <x>310.0</x>
    <y>5.5</y>
   </point>
   <point>
    <x>315.0</x>
    <y>5.5</y>
   </point>
   <point>
    <x>320.0</x>
    <y>5.5</y>
   </point>
   <point>
    <x>325.0</x>
    <y>5.5</y>
   </point>
   <point>
    <x>330.0</x>
    <y>5.5</y>
   </point>
   <point>
    <x>335.0</x>
    <y>5.5</y>
   </point>
   <point>
    <x>340.0</x>
    <y>5.5</y>
   </point>
   <point>
    <x>345.0</x>
    <y>5.5</y>
   </point>
   <point>
    <x>350.0</x>
    <y>5.5</y>
   </point>
   <point>
    <x>355.0</x>
    <y>5.5</y>
   </point>
   <point>
    <x>360.0</x>
    <y>5.5</y>
   </point>
   <point>
    <x>365.0</x>
    <y>5.5</y>
   </point>
   <point>
    <x>370.0</x>
    <y>5.5</y>
   </point>
   <point>
    <x>375.0</x>
    <y>5.5</y>
   </point>
   <point>
    <x>380.0</x>
    <y>5.5</y>
   </point>
   <point>
    <x>385.0</x>
    <y>5.5</y>
   </point>
   <point>
    <x>390.0</x>
    <y>5.5</y>
   </point>
   <point>
    <x>395.0</x>
    <y>5.5</y>
   </point>
   <point>
    <x>400.0</x>
    <y>5.5</y>
   </point>
   <lineMarking>solid</lineMarking>
  </leftBound>
  <rightBound>
   <point>
    <x>-50.0</x>
    <y>2.0</y>
   </point>
   <point>
    <x>-45.0</x>
    <y>2.0</y>
   </point>
   <point>
    <x>-40.0</x>
    <y>2.0</y>
   </point>
   <point>
    <x>-35.0</x>
    <y>2.0</y>
   </point>
   <point>
    <x>-30.0</x>
    <y>2.0</y>
   </point>
   <point>
    <x>-25.0</x>
    <y>2.0</y>
   </point>
   <point>
    <x>-20.0</x>
    <y>2.0</y>
   </point>
   <point>
    <x>-15.0</x>
    <y>2.0</y>
   </point>
   <point>
    <x>-10.0</x>
    <y>2.0</y>
   </point>
   <point>
    <x>-5.0</x>
    <y>2.0</y>
   </point>
   <point>
    <x>0.0</x>
    <y>2.0</y>
   </point>
   <point>
    <x>5.0</x>
    <y>2.0</y>
   </point>
   <point>
    <x>10.0</x>
    <y>2.0</y>
   </point>
   <point>
    <x>15.0</x>
    <y>2.0</y>
   </point>
   <point>
    <x>20.0</x>
    <y>2.0</y>
   </point>
   <point>
    <x>25.0</x>
    <y>2.0</y>
   </point>
   <point>
    <x>30.0</x>
    <y>2.0</y>
   </point>
   <point>
    <x>35.0</x>
    <y>2.0</y>
   </point>
   <point>
    <x>40.0</x>
    <y>2.0</y>
   </point>
   <point>
    <x>45.0</x>
    <y>2.0</y>
   </point>
   <point>
    <x>50.0</x>
    <y>2.0</y>
   </point>
   <point>
    <x>55.0</x>
    <y>2.0</y>
   </point>
   <point>
    <x>60.0</x>
    <y>2.0</y>
   </point>
   <point>
    <x>65.0</x>
    <y>2.0</y>
   </point>
   <point>
    <x>70.0</x>
    <y>2.0</y>
   </point>
   <point>
    <x>75.0</x>
    <y>2.0</y>
   </point>
   <point>
    <x>80.0</x>
    <y>2.0</y>
   </point>
   <point>
    <x>85.0</x>
    <y>2.0</y>
   </point>
   <point>
    <x>90.0</x>
    <y>2.0</y>
   </point>
   <point>
    <x>95.0</x>
    <y>2.0</y>
   </point>
   <point>
    <x>100.0</x>
    <y>2.0</y>
   </point>
   <point>
    <x>105.0</x>
    <y>2.0</y>
   </point>
   <point>
    <x>110.0</x>
    <y>2.0</y>
   </point>
   <point>
    <x>115.0</x>
    <y>2.0</y>
   </point>
   <point>
    <x>120.0</x>
    <y>2.0</y>
   </point>
   <point>
    <x>125.0</x>
    <y>2.0</y>
   </point>
   <point>
    <x>130.0</x>
    <y>2.0</y>
   </point>
   <point>
    <x>135.0</x>
    <y>2.0</y>
   </point>
   <point>
    <x>140.0</x>
    <y>2.0</y>
   </point>
   <point>
    <x>145.0</x>
    <y>2.0</y>
   </point>
   <point>
    <x>150.0</x>
    <y>2.0</y>
   </point>
   <point>
    <x>155.0</x>
    <y>2.0</y>
   </point>
   <point>
    <x>160.0</x>
    <y>2.0</y>
   </point>
   <point>
    <x>165.0</x>
    <y>2.0</y>
   </point>
   <point>
    <x>170.0</x>
    <y>2.0</y>
   </point>
   <point>
    <x>175.0</x>
    <y>2.0</y>
   </point>
   <point>
    <x>180.0</x>
    <y>2.0</y>
   </point>
   <point>
    <x>185.0</x>
    <y>2.0</y>
   </point>
   <point>
    <x>190.0</x>
    <y>2.0</y>
   </point>
   <point>
    <x>195.0</x>
    <y>2.0</y>
   </point>
   <point>
    <x>200.0</x>
    <y>2.0</y>
   </point>
   <point>
    <x>205.0</x>
    <y>2.0</y>
   </point>
   <point>
    <x>210.0</x>
    <y>2.0</y>
   </point>
   <point>
    <x>215.0</x>
    <y>2.0</y>
   </point>
   <point>
    <x>220.0</x>
    <y>2.0</y>
   </point>
   <point>
    <x>225.0</x>
    <y>2.0</y>
   </point>
   <point>
    <x>230.0</x>
    <y>2.0</y>
   </point>
   <point>
    <x>235.0</x>
    <y>2.0</y>
   </point>
   <point>
    <x>240.0</x>
    <y>2.0</y>
   </point>
   <point>
    <x>245.0</x>
    <y>2.0</y>
   </point>
   <point>
    <x>250.0</x>
    <y>2.0</y>
   </point>
   <point>
    <x>255.0</x>
    <y>2.0</y>
   </point>
   <point>
    <x>260.0</x>
    <y>2.0</y>
   </point>
   <point>
    <x>265.0</x>
    <y>2.0</y>
   </point>
   <point>
    <x>270.0</x>
    <y>2.0</y>
   </point>
   <point>
    <x>275.0</x>
    <y>2.0</y>
   </point>
   <point>
    <x>280.0</x>
    <y>2.0</y>
   </point>
   <point>
    <x>285.0</x>
    <y>2.0</y>
   </point>
   <point>
    <x>290.0</x>
    <y>2.0</y>
   </point>
   <point>
    <x>295.0</x>
    <y>2.0</y>
   </point>
   <point>
    <x>300.0</x>
    <y>2.0</y>
   </point>
   <point>
    <x>305.0</x>
    <y>2.0</y>
   </point>
   <point>
    <x>310.0</x>
    <y>2.0</y>
   </point>
   <point>
    <x>315.0</x>
    <y>2.0</y>
   </point>
   <point>
    <x>320.0</x>
    <y>2.0</y>
   </point>
   <point>
    <x>325.0</x>
    <y>2.0</y>
   </point>
   <point>
    <x>330.0</x>
    <y>2.0</y>
   </point>
   <point>
    <x>335.0</x>
    <y>2.0</y>
   </point>
   <point>
    <x>340.0</x>
    <y>2.0</y>
   </point>
   <point>
    <x>345.0</x>
    <y>2.0</y>
   </point>
   <point>
    <x>350.0</x>
    <y>2.0</y>
   </point>
   <point>
    <x>355.0</x>
    <y>2.0</y>
   </point>
   <point>
    <x>360.0</x>
    <y>2.0</y>
   </point>
   <point>
    <x>365.0</x>
    <y>2.0</y>
   </point>
   <point>
    <x>370.0</x>
    <y>2.0</y>
   </point>
   <point>
    <x>375.0</x>
    <y>2.0</y>
   </point>
   <point>
    <x>380.0</x>
    <y>2.0</y>
   </point>
   <point>
    <x>385.0</x>
    <y>2.0</y>
   </point>
   <point>
    <x>390.0</x>
    <y>2.0</y>
   </point>
   <point>
    <x>395.0</x>
    <y>2.0</y>
   </point>
   <point>
    <x>400.0</x>
    <y>2.0</y>
   </point>
   <lineMarking>dashed</lineMarking>
  </rightBound>
  <adjacentRight ref="100" drivingDir="same" />
  <laneletType>urban</laneletType>
 </lanelet>
 <dynamicObstacle id="200">
  <type>car</type>
  <shape>
   <rectangle>
    <length>4.5</length>
    <width>1.8</width>
   </rectangle>
  </shape>
  <initialState>
   <position>
    <point>
     <x>25.0</x>
     <y>4.0</y>
    </point>
   </position>
   <orientation>
    <exact>0.0</exact>
   </orientation>
   <time>
    <exact>0</exact>
   </time>
   <velocity>
    <exact>9.0</exact>
   </velocity>
  </initialState>
  <trajectory>
   <state>
    <position>
     <point>
      <x>25.9</x>
      <y>4.0</y>
     </point>
    </position>
    <orientation>
     <exact>0.0</exact>
    </orientation>
    <time>
     <exact>1</exact>
    </time>
    <velocity>
     <exact>9.0</exact>
    </velocity>
   </state>
   <state>
    <position>
     <point>
      <x>26.8</x>
      <y>4.0</y>
     </point>
    </position>
    <orientation>
     <exact>0.0</exact>
    </orientation>
    <time>
     <exact>2</exact>
    </time>
    <velocity>
     <exact>9.0</exact>
    </velocity>
   </state>
   <state>
    <position>
     <point>
      <x>27.7</x>
      <y>4.0</y>
     </point>
    </position>
    <orientation>
     <exact>0.0</exact>
    </orientation>
    <time>
     <exact>3</exact>
    </time>
    <velocity>
     <exact>9.0</exact>
    </velocity>
   </state>
   <state>
    <position>
     <point>
      <x>28.6</x>
      <y>4.0</y>
     </point>
    </position>
    <orientation>
     <exact>0.0</exact>
    </orientation>
    <time>
     <exact>4</exact>
    </time>
    <velocity>
     <exact>9.0</exact>
    </velocity>
   </state>
   <state>
    <position>
     <point>
      <x>29.5</x>
      <y>4.0</y>
     </point>
    </position>
    <orientation>
     <exact>0.0</exact>
    </orientation>
    <time>
     <exact>5</exact>
    </time>
    <velocity>
     <exact>9.0</exact>
    </velocity>
   </state>
   <state>
    <position>
     <point>
      <x>30.4</x>
      <y>4.0</y>
     </point>
    </position>
    <orientation>
     <exact>0.0</exact>
    </orientation>
    <time>
     <exact>6</exact>
    </time>
    <velocity>
     <exact>9.0</exact>
    </velocity>
   </state>
   <state>
    <position>
     <point>
      <x>31.3</x>
      <y>4.0</y>
     </point>
    </position>
    <orientation>
     <exact>0.0</exact>
    </orientation>
    <time>
     <exact>7</exact>
    </time>
    <velocity>
     <exact>9.0</exact>
    </velocity>
   </state>
   <state>
    <position>
     <point>
      <x>32.2</x>
      <y>4.0</y>
     </point>
    </position>
    <orientation>
     <exact>0.0</exact>
    </orientation>
    <time>
     <exact>8</exact>
    </time>
    <velocity>
     <exact>9.0</exact>
    </velocity>
   </state>
   <state>
    <position>
     <point>
      <x>33.1</x>
      <y>4.0</y>
     </point>
    </position>
    <orientation>
     <exact>0.0</exact>
    </orientation>
    <time>
     <exact>9</exact>
    </time>
    <velocity>
     <exact>9.0</exact>
    </velocity>
   </state>
   <state>
    <position>
     <point>
      <x>34.0</x>
      <y>4.0</y>
     </point>
    </position>
    <orientation>
     <exact>0.0</exact>
    </orientation>
    <time>
     <exact>10</exact>
    </time>
    <velocity>
     <exact>9.0</exact>
    </velocity>
   </state>
   <state>
    <position>
     <point>
      <x>34.9</x>
      <y>4.0</y>
     </point>
    </position>
    <orientation>
     <exact>0.0</exact>
    </orientation>
    <time>
     <exact>11</exact>
    </time>
    <velocity>
     <exact>9.0</exact>
    </velocity>
   </state>
   <state>
    <position>
     <point>
      <x>35.8</x>
      <y>4.0</y>
     </point>
    </position>
    <orientation>
     <exact>0.0</exact>
    </orientation>
    <time>
     <exact>12</exact>
    </time>
    <velocity>
     <exact>9.0</exact>
    </velocity>
   </state>
   <state>
    <position>
     <point>
      <x>36.7</x>
      <y>4.0</y>
     </point>
    </position>
    <orientation>
     <exact>0.0</exact>
    </orientation>
    <time>
     <exact>13</exact>
    </time>
    <velocity>
     <exact>9.0</exact>
    </velocity>
   </state>
   <state>
    <position>
     <point>
      <x>37.6</x>
      <y>4.0</y>
     </point>
    </position>
    <orientation>
     <exact>0.0</exact>
    </orientation>
    <time>
     <exact>14</exact>
    </time>
    <velocity>
     <exact>9.0</exact>
    </velocity>
   </state>
   <state>
    <position>
     <point>
      <x>38.5</x>
      <y>4.0</y>
     </point>
    </position>
    <orientation>
     <exact>0.0</exact>
    </orientation>
    <time>
     <exact>15</exact>
    </time>
    <velocity>
     <exact>9.0</exact>
    </velocity>
   </state>
   <state>
    <position>
     <point>
      <x>39.4</x>
      <y>4.0</y>
     </point>
    </position>
    <orientation>
     <exact>0.0</exact>
    </orientation>
    <time>
     <exact>16</exact>
    </time>
    <velocity>
     <exact>9.0</exact>
    </velocity>
   </state>
   <state>
    <position>
     <point>
      <x>40.3</x>
      <y>4.0</y>
     </point>
    </position>
    <orientation>
     <exact>0.0</exact>
    </orientation>
    <time>
     <exact>17</exact>
    </time>
    <velocity>
     <exact>9.0</exact>
    </velocity>
   </state>
   <state>
    <position>
     <point>
      <x>41.2</x>
      <y>4.0</y>
     </point>
    </position>
    <orientation>
     <exact>0.0</exact>
    </orientation>
    <time>
     <exact>18</exact>
    </time>
    <velocity>
     <exact>9.0</exact>
    </velocity>
   </state>
   <state>
    <position>
     <point>
      <x>42.1</x>
      <y>4.0</y>
     </point>
    </position>
    <orientation>
     <exact>0.0</exact>
    </orientation>
    <time>
     <exact>19</exact>
    </time>
    <velocity>
     <exact>9.0</exact>
    </velocity>
   </state>
   <state>
    <position>
     <point>
      <x>43.0</x>
      <y>4.0</y>
     </point>
    </position>
    <orientation>
     <exact>0.0</exact>
    </orientation>
    <time>
     <exact>20</exact>
    </time>
    <velocity>
     <exact>9.0</exact>
    </velocity>
   </state>
   <state>
    <position>
     <point>
      <x>43.9</x>
      <y>4.0</y>
     </point>
    </position>
    <orientation>
     <exact>-0.0198</exact>
    </orientation>
    <time>
     <exact>21</exact>
    </time>
    <velocity>
     <exact>9.0</exact>
    </velocity>
   </state>
   <state>
    <position>
     <point>
      <x>44.8</x>
      <y>3.982</y>
     </point>
    </position>
    <orientation>
     <exact>-0.0396</exact>
    </orientation>
    <time>
     <exact>22</exact>
    </time>
    <velocity>
     <exact>9.0</exact>
    </velocity>
   </state>
   <state>
    <position>
     <point>
      <x>45.699</x>
      <y>3.947</y>
     </point>
    </position>
    <orientation>
     <exact>-0.0594</exact>
    </orientation>
    <time>
     <exact>23</exact>
    </time>
    <velocity>
     <exact>9.0</exact>
    </velocity>
   </state>
   <state>
    <position>
     <point>
      <x>46.598</x>
      <y>3.893</y>
     </point>
    </position>
    <orientation>
     <exact>-0.0792</exact>
    </orientation>
    <time>
     <exact>24</exact>
    </time>
    <velocity>
     <exact>9.0</exact>
    </velocity>
   </state>
   <state>
    <position>
     <point>
      <x>47.495</x>
      <y>3.822</y>
     </point>
    </position>
    <orientation>
     <exact>-0.099</exact>
    </orientation>
    <time>
     <exact>25</exact>
    </time>
    <velocity>
     <exact>9.0</exact>
    </velocity>
   </state>
   <state>
    <position>
     <point>
      <x>48.39</x>
      <y>3.733</y>
     </point>
    </position>
    <orientation>
     <exact>-0.1188</exact>
    </orientation>
    <time>
     <exact>26</exact>
    </time>
    <velocity>
     <exact>9.0</exact>
    </velocity>
   </state>
   <state>
    <position>
     <point>
      <x>49.284</x>
      <y>3.626</y>
     </point>
    </position>
    <orientation>
     <exact>-0.1386</exact>
    </orientation>
    <time>
     <exact>27</exact>
    </time>
    <velocity>
     <exact>9.0</exact>
    </velocity>
   </state>
   <state>
    <position>
     <point>
      <x>50.175</x>
      <y>3.502</y>
     </point>
    </position>
    <orientation>
     <exact>-0.1584</exact>
    </orientation>
    <time>
     <exact>28</exact>
    </time>
    <velocity>
     <exact>9.0</exact>
    </velocity>
   </state>
   <state>
    <position>
     <point>
      <x>51.064</x>
      <y>3.36</y>
     </point>
    </position>
    <orientation>
     <exact>-0.1782</exact>
    </orientation>
    <time>
     <exact>29</exact>
    </time>
    <velocity>
     <exact>9.0</exact>
    </velocity>
   </state>
   <state>
    <position>
     <point>
      <x>51.95</x>
      <y>3.2</y>
     </point>
    </position>
    <orientation>
     <exact>-0.198</exact>
    </orientation>
    <time>
     <exact>30</exact>
    </time>
    <velocity>
     <exact>9.0</exact>
    </velocity>
   </state>
   <state>
    <position>
     <point>
      <x>52.832</x>
      <y>3.023</y>
     </point>
    </position>
    <orientation>
     <exact>-0.2178</exact>
    </orientation>
    <time>
     <exact>31</exact>
    </time>
    <velocity>
     <exact>9.0</exact>
    </velocity>
   </state>
   <state>
    <position>
     <point>
      <x>53.711</x>
      <y>2.829</y>
     </point>
    </position>
    <orientation>
     <exact>-0.2376</exact>
    </orientation>
    <time>
     <exact>32</exact>
    </time>
    <velocity>
     <exact>9.0</exact>
    </velocity>
   </state>
   <state>
    <position>
     <point>
      <x>54.586</x>
      <y>2.617</y>
     </point>
    </position>
    <orientation>
     <exact>-0.2574</exact>
    </orientation>
    <time>
     <exact>33</exact>
    </time>
    <velocity>
     <exact>9.0</exact>
    </velocity>
   </state>
   <state>
    <position>
     <point>
      <x>55.456</x>
      <y>2.388</y>
     </point>
    </position>
    <orientation>
     <exact>-0.2772</exact>
    </orientation>
    <time>
     <exact>34</exact>
    </time>
    <velocity>
     <exact>9.0</exact>
    </velocity>
   </state>
   <state>
    <position>
     <point>
      <x>56.322</x>
      <y>2.142</y>
     </point>
    </position>
    <orientation>
     <exact>-0.297</exact>
    </orientation>
    <time>
     <exact>35</exact>
    </time>
    <velocity>
     <exact>9.0</exact>
    </velocity>
   </state>
   <state>
    <position>
     <point>
      <x>57.182</x>
      <y>1.878</y>
     </point>
    </position>
    <orientation>
     <exact>-0.2772</exact>
    </orientation>
    <time>
     <exact>36</exact>
    </time>
    <velocity>
     <exact>9.0</exact>
    </velocity>
   </state>
   <state>
    <position>
     <point>
      <x>58.048</x>
      <y>1.632</y>
     </point>
    </position>
    <orientation>
     <exact>-0.2574</exact>
    </orientation>
    <time>
     <exact>37</exact>
    </time>
    <velocity>
     <exact>9.0</exact>
    </velocity>
   </state>
   <state>
    <position>
     <point>
      <x>58.918</x>
      <y>1.403</y>
     </point>
    </position>
    <orientation>
     <exact>-0.2376</exact>
    </orientation>
    <time>
     <exact>38</exact>
    </time>
    <velocity>
     <exact>9.0</exact>
    </velocity>
   </state>
   <state>
    <position>
     <point>
      <x>59.793</x>
      <y>1.191</y>
     </point>
    </position>
    <orientation>
     <exact>-0.2178</exact>
    </orientation>
    <time>
     <exact>39</exact>
    </time>
    <velocity>
     <exact>9.0</exact>
    </velocity>
   </state>
   <state>
    <position>
     <point>
      <x>60.672</x>
      <y>0.997</y>
     </point>
    </position>
    <orientation>
     <exact>-0.198</exact>
    </orientation>
    <time>
     <exact>40</exact>
    </time>
    <velocity>
     <exact>9.0</exact>
    </velocity>
   </state>
   <state>
    <position>
     <point>
      <x>61.554</x>
      <y>0.82</y>
     </point>
    </position>
    <orientation>
     <exact>-0.1782</exact>
    </orientation>
    <time>
     <exact>41</exact>
    </time>
    <velocity>
     <exact>9.0</exact>
    </velocity>
   </state>
   <state>
    <position>
     <point>
      <x>62.44</x>
      <y>0.66</y>
     </point>
    </position>
    <orientation>
     <exact>-0.1584</exact>
    </orientation>
    <time>
     <exact>42</exact>
    </time>
    <velocity>
     <exact>9.0</exact>
    </velocity>
   </state>
   <state>
    <position>
     <point>
      <x>63.329</x>
      <y>0.518</y>
     </point>
    </position>
    <orientation>
     <exact>-0.1386</exact>
    </orientation>
    <time>
     <exact>43</exact>
    </time>
    <velocity>
     <exact>9.0</exact>
    </velocity>
   </state>
   <state>
    <position>
     <point>
      <x>64.22</x>
      <y>0.394</y>
     </point>
    </position>
    <orientation>
     <exact>-0.1188</exact>
    </orientation>
    <time>
     <exact>44</exact>
    </time>
    <velocity>
     <exact>9.0</exact>
    </velocity>
   </state>
   <state>
    <position>
     <point>
      <x>65.114</x>
      <y>0.287</y>
     </point>
    </position>
    <orientation>
     <exact>-0.099</exact>
    </orientation>
    <time>
     <exact>45</exact>
    </time>
    <velocity>
     <exact>9.0</exact>
    </velocity>
   </state>
   <state>
    <position>
     <point>
      <x>66.009</x>
      <y>0.198</y>
     </point>
    </position>
    <orientation>
     <exact>-0.0792</exact>
    </orientation>
    <time>
     <exact>46</exact>
    </time>
    <velocity>
     <exact>9.0</exact>
    </velocity>
   </state>
   <state>
    <position>
     <point>
      <x>66.906</x>
      <y>0.127</y>
     </point>
    </position>
    <orientation>
     <exact>-0.0594</exact>
    </orientation>
    <time>
     <exact>47</exact>
    </time>
    <velocity>
     <exact>9.0</exact>
    </velocity>
   </state>
   <state>
    <position>
     <point>
      <x>67.805</x>
      <y>0.073</y>
     </point>
    </position>
    <orientation>
     <exact>-0.0396</exact>
    </orientation>
    <time>
     <exact>48</exact>
    </time>
    <velocity>
     <exact>9.0</exact>
    </velocity>
   </state>
   <state>
    <position>
     <point>
      <x>68.704</x>
      <y>0.038</y>
     </point>
    </position>
    <orientation>
     <exact>-0.0198</exact>
    </orientation>
    <time>
     <exact>49</exact>
    </time>
    <velocity>
     <exact>9.0</exact>
    </velocity>
   </state>
   <state>
    <position>
     <point>
      <x>69.604</x>
      <y>0.02</y>
     </point>
    </position>
    <orientation>
     <exact>-0.0</exact>
    </orientation>
    <time>
     <exact>50</exact>
    </time>
    <velocity>
     <exact>9.0</exact>
    </velocity>
   </state>
   <state>
    <position>
     <point>
      <x>70.504</x>
      <y>0.02</y>
     </point>
    </position>
    <orientation>
     <exact>-0.0</exact>
    </orientation>
    <time>
     <exact>51</exact>
    </time>
    <velocity>
     <exact>8.9</exact>
    </velocity>
   </state>
   <state>
    <position>
     <point>
      <x>71.394</x>
      <y>0.02</y>
     </point>
    </position>
    <orientation>
     <exact>-0.0</exact>
    </orientation>
    <time>
     <exact>52</exact>
    </time>
    <velocity>
     <exact>8.8</exact>
    </velocity>
   </state>
   <state>
    <position>
     <point>
      <x>72.274</x>
      <y>0.02</y>
     </point>
    </position>
    <orientation>
     <exact>-0.0</exact>
    </orientation>
    <time>
     <exact>53</exact>
    </time>
    <velocity>
     <exact>8.7</exact>
    </velocity>
   </state>
   <state>
    <position>
     <point>
      <x>73.144</x>
      <y>0.02</y>
     </point>
    </position>
    <orientation>
     <exact>-0.0</exact>
    </orientation>
    <time>
     <exact>54</exact>
    </time>
    <velocity>
     <exact>8.6</exact>
    </velocity>
   </state>
   <state>
    <position>
     <point>
      <x>74.004</x>
      <y>0.02</y>
     </point>
    </position>
    <orientation>
     <exact>-0.0</exact>
    </orientation>
    <time>
     <exact>55</exact>
    </time>
    <velocity>
     <exact>8.5</exact>
    </velocity>
   </state>
   <state>
    <position>
     <point>
      <x>74.854</x>
      <y>0.02</y>
     </point>
    </position>
    <orientation>
     <exact>-0.0</exact>
    </orientation>
    <time>
     <exact>56</exact>
    </time>
    <velocity>
     <exact>8.4</exact>
    </velocity>
   </state>
   <state>
    <position>
     <point>
      <x>75.694</x>
      <y>0.02</y>
     </point>
    </position>
    <orientation>
     <exact>-0.0</exact>
    </orientation>
    <time>
     <exact>57</exact>
    </time>
    <velocity>
     <exact>8.3</exact>
    </velocity>
   </state>
   <state>
    <position>
     <point>
      <x>76.524</x>
      <y>0.02</y>
     </point>
    </position>
    <orientation>
     <exact>-0.0</exact>
    </orientation>
    <time>
     <exact>58</exact>
    </time>
    <velocity>
     <exact>8.2</exact>
    </velocity>
   </state>
   <state>
    <position>
     <point>
      <x>77.344</x>
      <y>0.02</y>
     </point>
    </position>
    <orientation>
     <exact>-0.0</exact>
    </orientation>
    <time>
     <exact>59</exact>
    </time>
    <velocity>
     <exact>8.1</exact>
    </velocity>
   </state>
   <state>
    <position>
     <point>
      <x>78.154</x>
      <y>0.02</y>
     </point>
    </position>
    <orientation>
     <exact>-0.0</exact>
    </orientation>
    <time>
     <exact>60</exact>
    </time>
    <velocity>
     <exact>8.0</exact>
    </velocity>
   </state>
   <state>
    <position>
     <point>
      <x>78.954</x>
      <y>0.02</y>
     </point>
    </position>
    <orientation>
     <exact>-0.0</exact>
    </orientation>
    <time>
     <exact>61</exact>
    </time>
    <velocity>
     <exact>7.9</exact>
    </velocity>
   </state>
   <state>
    <position>
     <point>
      <x>79.744</x>
      <y>0.02</y>
     </point>
    </position>
    <orientation>
     <exact>-0.0</exact>
    </orientation>
    <time>
     <exact>62</exact>
    </time>
    <velocity>
     <exact>7.8</exact>
    </velocity>
   </state>
   <state>
    <position>
     <point>
      <x>80.524</x>
      <y>0.02</y>
     </point>
    </position>
    <orientation>
     <exact>-0.0</exact>
    </orientation>
    <time>
     <exact>63</exact>
    </time>
    <velocity>
     <exact>7.7</exact>
    </velocity>
   </state>
   <state>
    <position>
     <point>
      <x>81.294</x>
      <y>0.02</y>
     </point>
    </position>
    <orientation>
     <exact>-0.0</exact>
    </orientation>
    <time>
     <exact>64</exact>
    </time>
    <velocity>
     <exact>7.6</exact>
    </velocity>
   </state>
   <state>
    <position>
     <point>
      <x>82.054</x>
      <y>0.02</y>
     </point>
    </position>
    <orientation>
     <exact>-0.0</exact>
    </orientation>
    <time>
     <exact>65</exact>
    </time>
    <velocity>
     <exact>7.5</exact>
    </velocity>
   </state>
   <state>
    <position>
     <point>
      <x>82.804</x>
      <y>0.02</y>
     </point>
    </position>
    <orientation>
     <exact>-0.0</exact>
    </orientation>
    <time>
     <exact>66</exact>
    </time>
    <velocity>
     <exact>7.4</exact>
    </velocity>
   </state>
   <state>
    <position>
     <point>
      <x>83.544</x>
      <y>0.02</y>
     </point>
    </position>
    <orientation>
     <exact>-0.0</exact>
    </orientation>
    <time>
     <exact>67</exact>
    </time>
    <velocity>
     <exact>7.3</exact>
    </velocity>
   </state>
   <state>
    <position>
     <point>
      <x>84.274</x>
      <y>0.02</y>
     </point>
    </position>
    <orientation>
     <exact>-0.0</exact>
    </orientation>
    <time>
     <exact>68</exact>
    </time>
    <velocity>
     <exact>7.2</exact>
    </velocity>
   </state>
   <state>
    <position>
     <point>
      <x>84.994</x>
      <y>0.02</y>
     </point>
    </position>
    <orientation>
     <exact>-0.0</exact>
    </orientation>
    <time>
     <exact>69</exact>
    </time>
    <velocity>
     <exact>7.1</exact>
    </velocity>
   </state>
   <state>
    <position>
     <point>
      <x>85.704</x>
      <y>0.02</y>
     </point>
    </position>
    <orientation>
     <exact>-0.0</exact>
    </orientation>
    <time>
     <exact>70</exact>
    </time>
    <velocity>
     <exact>7.0</exact>
    </velocity>
   </state>
   <state>
    <position>
     <point>
      <x>86.404</x>
      <y>0.02</y>
     </point>
    </position>
    <orientation>
     <exact>-0.0</exact>
    </orientation>
    <time>
     <exact>71</exact>
    </time>
    <velocity>
     <exact>6.9</exact>
    </velocity>
   </state>
   <state>
    <position>
     <point>
      <x>87.094</x>
      <y>0.02</y>
     </point>
    </position>
    <orientation>
     <exact>-0.0</exact>
    </orientation>
    <time>
     <exact>72</exact>
    </time>
    <velocity>
     <exact>6.9</exact>
    </velocity>
   </state>
   <state>
    <position>
     <point>
      <x>87.784</x>
      <y>0.02</y>
     </point>
    </position>
    <orientation>
     <exact>-0.0</exact>
    </orientation>
    <time>
     <exact>73</exact>
    </time>
    <velocity>
     <exact>6.9</exact>
    </velocity>
   </state>
   <state>
    <position>
     <point>
      <x>88.474</x>
      <y>0.02</y>
     </point>
    </position>
    <orientation>
     <exact>-0.0</exact>
    </orientation>
    <time>
     <exact>74</exact>
    </time>
    <velocity>
     <exact>6.9</exact>
    </velocity>
   </state>
   <state>
    <position>
     <point>
      <x>89.164</x>
      <y>0.02</y>
     </point>
    </position>
    <orientation>
     <exact>-0.0</exact>
    </orientation>
    <time>
     <exact>75</exact>
    </time>
    <velocity>
     <exact>6.9</exact>
    </velocity>
   </state>
   <state>
    <position>
     <point>
      <x>89.854</x>
      <y>0.02</y>
     </point>
    </position>
    <orientation>
     <exact>-0.0</exact>
    </orientation>
    <time>
     <exact>76</exact>
    </time>
    <velocity>
     <exact>6.9</exact>
    </velocity>
   </state>
   <state>
    <position>
     <point>
      <x>90.544</x>
      <y>0.02</y>
     </point>
    </position>
    <orientation>
     <exact>-0.0</exact>
    </orientation>
    <time>
     <exact>77</exact>
    </time>
    <velocity>
     <exact>6.9</exact>
    </velocity>
   </state>
   <state>
    <position>
     <point>
      <x>91.234</x>
      <y>0.02</y>
     </point>
    </position>
    <orientation>
     <exact>-0.0</exact>
    </orientation>
    <time>
     <exact>78</exact>
    </time>
    <velocity>
     <exact>6.9</exact>
    </velocity>
   </state>
   <state>
    <position>
     <point>
      <x>91.924</x>
      <y>0.02</y>
     </point>
    </position>
    <orientation>
     <exact>-0.0</exact>
    </orientation>
    <time>
     <exact>79</exact>
    </time>
    <velocity>
     <exact>6.9</exact>
    </velocity>
   </state>
   <state>
    <position>
     <point>
      <x>92.614</x>
      <y>0.02</y>
     </point>
    </position>
    <orientation>
     <exact>-0.0</exact>
    </orientation>
    <time>
     <exact>80</exact>
    </time>
    <velocity>
     <exact>6.9</exact>
    </velocity>
   </state>
   <state>
    <position>
     <point>
      <x>93.304</x>
      <y>0.02</y>
     </point>
    </position>
    <orientation>
     <exact>-0.0</exact>
    </orientation>
    <time>
     <exact>81</exact>
    </time>
    <velocity>
     <exact>6.9</exact>
    </velocity>
   </state>
   <state>
    <position>
     <point>
      <x>93.994</x>
      <y>0.02</y>
     </point>
    </position>
    <orientation>
     <exact>-0.0</exact>
    </orientation>
    <time>
     <exact>82</exact>
    </time>
    <velocity>
     <exact>6.9</exact>
    </velocity>
   </state>
   <state>
    <position>
     <point>
      <x>94.684</x>
      <y>0.02</y>
     </point>
    </position>
    <orientation>
     <exact>-0.0</exact>
    </orientation>
    <time>
     <exact>83</exact>
    </time>
    <velocity>
     <exact>6.9</exact>
    </velocity>
   </state>
   <state>
    <position>
     <point>
      <x>95.374</x>
      <y>0.02</y>
     </point>
    </position>
    <orientation>
     <exact>-0.0</exact>
    </orientation>
    <time>
     <exact>84</exact>
    </time>
    <velocity>
     <exact>6.9</exact>
    </velocity>
   </state>
   <state>
    <position>
     <point>
      <x>96.064</x>
      <y>0.02</y>
     </point>
    </position>
    <orientation>
     <exact>-0.0</exact>
    </orientation>
    <time>
     <exact>85</exact>
    </time>
    <velocity>
     <exact>6.9</exact>
    </velocity>
   </state>
   <state>
    <position>
     <point>
      <x>96.754</x>
      <y>0.02</y>
     </point>
    </position>
    <orientation>
     <exact>-0.0</exact>
    </orientation>
    <time>
     <exact>86</exact>
    </time>
    <velocity>
     <exact>6.9</exact>
    </velocity>
   </state>
   <state>
    <position>
     <point>
      <x>97.444</x>
      <y>0.02</y>
     </point>
    </position>
    <orientation>
     <exact>-0.0</exact>
    </orientation>
    <time>
     <exact>87</exact>
    </time>
    <velocity>
     <exact>6.9</exact>
    </velocity>
   </state>
   <state>
    <position>
     <point>
      <x>98.134</x>
      <y>0.02</y>
     </point>
    </position>
    <orientation>
     <exact>-0.0</exact>
    </orientation>
    <time>
     <exact>88</exact>
    </time>
    <velocity>
     <exact>6.9</exact>
    </velocity>
   </state>
   <state>
    <position>
     <point>
      <x>98.824</x>
      <y>0.02</y>
     </point>
    </position>
    <orientation>
     <exact>-0.0</exact>
    </orientation>
    <time>
     <exact>89</exact>
    </time>
    <velocity>
     <exact>6.9</exact>
    </velocity>
   </state>
   <state>
    <position>
     <point>
      <x>99.514</x>
      <y>0.02</y>
     </point>
    </position>
    <orientation>
     <exact>-0.0</exact>
    </orientation>
    <time>
     <exact>90</exact>
    </time>
    <velocity>
     <exact>6.9</exact>
    </velocity>
   </state>
   <state>
    <position>
     <point>
      <x>100.204</x>
      <y>0.02</y>
     </point>
    </position>
    <orientation>
     <exact>-0.0</exact>
    </orientation>
    <time>
     <exact>91</exact>
    </time>
    <velocity>
     <exact>6.9</exact>
    </velocity>
   </state>
   <state>
    <position>
     <point>
      <x>100.894</x>
      <y>0.02</y>
     </point>
    </position>
    <orientation>
     <exact>-0.0</exact>
    </orientation>
    <time>
     <exact>92</exact>
    </time>
    <velocity>
     <exact>6.9</exact>
    </velocity>
   </state>
   <state>
    <position>
     <point>
      <x>101.584</x>
      <y>0.02</y>
     </point>
    </position>
    <orientation>
     <exact>-0.0</exact>
    </orientation>
    <time>
     <exact>93</exact>
    </time>
    <velocity>
     <exact>6.9</exact>
    </velocity>
   </state>
   <state>
    <position>
     <point>
      <x>102.274</x>
      <y>0.02</y>
     </point>
    </position>
    <orientation>
     <exact>-0.0</exact>
    </orientation>
    <time>
     <exact>94</exact>
    </time>
    <velocity>
     <exact>6.9</exact>
    </velocity>
   </state>
   <state>
    <position>
     <point>
      <x>102.964</x>
      <y>0.02</y>
     </point>
    </position>
    <orientation>
     <exact>-0.0</exact>
    </orientation>
    <time>
     <exact>95</exact>
    </time>
    <velocity>
     <exact>6.9</exact>
    </velocity>
   </state>
   <state>
    <position>
     <point>
      <x>103.654</x>
      <y>0.02</y>
     </point>
    </position>
    <orientation>
     <exact>-0.0</exact>
    </orientation>
    <time>
     <exact>96</exact>
    </time>
    <velocity>
     <exact>6.9</exact>
    </velocity>
   </state>
   <state>
    <position>
     <point>
      <x>104.344</x>
      <y>0.02</y>
     </point>
    </position>
    <orientation>
     <exact>-0.0</exact>
    </orientation>
    <time>
     <exact>97</exact>
    </time>
    <velocity>
     <exact>6.9</exact>
    </velocity>
   </state>
   <state>
    <position>
     <point>
      <x>105.034</x>
      <y>0.02</y>
     </point>
    </position>
    <orientation>
     <exact>-0.0</exact>
    </orientation>
    <time>
     <exact>98</exact>
    </time>
    <velocity>
     <exact>6.9</exact>
    </velocity>
   </state>
   <state>
    <position>
     <point>
      <x>105.724</x>
      <y>0.02</y>
     </point>
    </position>
    <orientation>
     <exact>-0.0</exact>
    </orientation>
    <time>
     <exact>99</exact>
    </time>
    <velocity>
     <exact>6.9</exact>
    </velocity>
   </state>
   <state>
    <position>
     <point>
      <x>106.414</x>
      <y>0.02</y>
     </point>
    </position>
    <orientation>
     <exact>-0.0</exact>
    </orientation>
    <time>
     <exact>100</exact>
    </time>
    <velocity>
     <exact>6.9</exact>
    </velocity>
   </state>
   <state>
    <position>
     <point>
      <x>107.104</x>
      <y>0.02</y>
     </point>
    </position>
    <orientation>
     <exact>-0.0</exact>
    </orientation>
    <time>
     <exact>101</exact>
    </time>
    <velocity>
     <exact>6.9</exact>
    </velocity>
   </state>
   <state>
    <position>
     <point>
      <x>107.794</x>
      <y>0.02</y>
     </point>
    </position>
    <orientation>
     <exact>-0.0</exact>
    </orientation>
    <time>
     <exact>102</exact>
    </time>
    <velocity>
     <exact>6.9</exact>
    </velocity>
   </state>
   <state>
    <position>
     <point>
      <x>108.484</x>
      <y>0.02</y>
     </point>
    </position>
    <orientation>
     <exact>-0.0</exact>
    </orientation>
    <time>
     <exact>103</exact>
    </time>
    <velocity>
     <exact>6.9</exact>
    </velocity>
   </state>
   <state>
    <position>
     <point>
      <x>109.174</x>
      <y>0.02</y>
     </point>
    </position>
    <orientation>
     <exact>-0.0</exact>
    </orientation>
    <time>
     <exact>104</exact>
    </time>
    <velocity>
     <exact>6.9</exact>
    </velocity>
   </state>
   <state>
    <position>
     <point>
      <x>109.864</x>
      <y>0.02</y>
     </point>
    </position>
    <orientation>
     <exact>-0.0</exact>
    </orientation>
    <time>
     <exact>105</exact>
    </time>
    <velocity>
     <exact>6.9</exact>
    </velocity>
   </state>
   <state>
    <position>
     <point>
      <x>110.554</x>
      <y>0.02</y>
     </point>
    </position>
    <orientation>
     <exact>-0.0</exact>
    </orientation>
    <time>
     <exact>106</exact>
    </time>
    <velocity>
     <exact>6.9</exact>
    </velocity>
   </state>
   <state>
    <position>
     <point>
      <x>111.244</x>
      <y>0.02</y>
     </point>
    </position>
    <orientation>
     <exact>-0.0</exact>
    </orientation>
    <time>
     <exact>107</exact>
    </time>
    <velocity>
     <exact>6.9</exact>
    </velocity>
   </state>
   <state>
    <position>
     <point>
      <x>111.934</x>
      <y>0.02</y>
     </point>
    </position>
    <orientation>
     <exact>-0.0</exact>
    </orientation>
    <time>
     <exact>108</exact>
    </time>
    <velocity>
     <exact>6.9</exact>
    </velocity>
   </state>
   <state>
    <position>
     <point>
      <x>112.624</x>
      <y>0.02</y>
     </point>
    </position>
    <orientation>
     <exact>-0.0</exact>
    </orientation>
    <time>
     <exact>109</exact>
    </time>
    <velocity>
     <exact>6.9</exact>
    </velocity>
   </state>
   <state>
    <position>
     <point>
      <x>113.314</x>
      <y>0.02</y>
     </point>
    </position>
    <orientation>
     <exact>-0.0</exact>
    </orientation>
    <time>
     <exact>110</exact>
    </time>
    <velocity>
     <exact>6.9</exact>
    </velocity>
   </state>
   <state>
    <position>
     <point>
      <x>114.004</x>
      <y>0.02</y>
     </point>
    </position>
    <orientation>
     <exact>-0.0</exact>
    </orientation>
    <time>
     <exact>111</exact>
    </time>
    <velocity>
     <exact>6.9</exact>
    </velocity>
   </state>
   <state>
    <position>
     <point>
      <x>114.694</x>
      <y>0.02</y>
     </point>
    </position>
    <orientation>
     <exact>-0.0</exact>
    </orientation>
    <time>
     <exact>112</exact>
    </time>
    <velocity>
     <exact>6.9</exact>
    </velocity>
   </state>
   <state>
    <position>
     <point>
      <x>115.384</x>
      <y>0.02</y>
     </point>
    </position>
    <orientation>
     <exact>-0.0</exact>
    </orientation>
    <time>
     <exact>113</exact>
    </time>
    <velocity>
     <exact>6.9</exact>
    </velocity>
   </state>
   <state>
    <position>
     <point>
      <x>116.074</x>
      <y>0.02</y>
     </point>
    </position>
    <orientation>
     <exact>-0.0</exact>
    </orientation>
    <time>
     <exact>114</exact>
    </time>
    <velocity>
     <exact>6.9</exact>
    </velocity>
   </state>
   <state>
    <position>
     <point>
      <x>116.764</x>
      <y>0.02</y>
     </point>
    </position>
    <orientation>
     <exact>-0.0</exact>
    </orientation>
    <time>
     <exact>115</exact>
    </time>
    <velocity>
     <exact>6.9</exact>
    </velocity>
   </state>
   <state>
    <position>
     <point>
      <x>117.454</x>
      <y>0.02</y>
     </point>
    </position>
    <orientation>
     <exact>-0.0</exact>
    </orientation>
    <time>
     <exact>116</exact>
    </time>
    <velocity>
     <exact>6.9</exact>
    </velocity>
   </state>
   <state>
    <position>
     <point>
      <x>118.144</x>
      <y>0.02</y>
     </point>
    </position>
    <orientation>
     <exact>-0.0</exact>
    </orientation>
    <time>
     <exact>117</exact>
    </time>
    <velocity>
     <exact>6.9</exact>
    </velocity>
   </state>
   <state>
    <position>
     <point>
      <x>118.834</x>
      <y>0.02</y>
     </point>
    </position>
    <orientation>
     <exact>-0.0</exact>
    </orientation>
    <time>
     <exact>118</exact>
    </time>
    <velocity>
     <exact>6.9</exact>
    </velocity>
   </state>
   <state>
    <position>
     <point>
      <x>119.524</x>
      <y>0.02</y>
     </point>
    </position>
    <orientation>
     <exact>-0.0</exact>
    </orientation>
    <time>
     <exact>119</exact>
    </time>
    <velocity>
     <exact>6.9</exact>
    </velocity>
   </state>
   <state>
    <position>
     <point>
      <x>120.214</x>
      <y>0.02</y>
     </point>
    </position>
    <orientation>
     <exact>-0.0</exact>
    </orientation>
    <time>
     <exact>120</exact>
    </time>
    <velocity>
     <exact>6.9</exact>
    </velocity>
   </state>
   <state>
    <position>
     <point>
      <x>120.904</x>
      <y>0.02</y>
     </point>
    </position>
    <orientation>
     <exact>-0.0</exact>
    </orientation>
    <time>
     <exact>121</exact>
    </time>
    <velocity>
     <exact>6.9</exact>
    </velocity>
   </state>
   <state>
    <position>
     <point>
      <x>121.594</x>
      <y>0.02</y>
     </point>
    </position>
    <orientation>
     <exact>-0.0</exact>
    </orientation>
    <time>
     <exact>122</exact>
    </time>
    <velocity>
     <exact>6.9</exact>
    </velocity>
   </state>
   <state>
    <position>
     <point>
      <x>122.284</x>
      <y>0.02</y>
     </point>
    </position>
    <orientation>
     <exact>-0.0</exact>
    </orientation>
    <time>
     <exact>123</exact>
    </time>
    <velocity>
     <exact>6.9</exact>
    </velocity>
   </state>
   <state>
    <position>
     <point>
      <x>122.974</x>
      <y>0.02</y>
     </point>
    </position>
    <orientation>
     <exact>-0.0</exact>
    </orientation>
    <time>
     <exact>124</exact>
    </time>
    <velocity>
     <exact>6.9</exact>
    </velocity>
   </state>
   <state>
    <position>
     <point>
      <x>123.664</x>
      <y>0.02</y>
     </point>
    </position>
    <orientation>
     <exact>-0.0</exact>
    </orientation>
    <time>
     <exact>125</exact>
    </time>
    <velocity>
     <exact>6.9</exact>
    </velocity>
   </state>
   <state>
    <position>
     <point>
      <x>124.354</x>
      <y>0.02</y>
     </point>
    </position>
    <orientation>
     <exact>-0.0</exact>
    </orientation>
    <time>
     <exact>126</exact>
    </time>
    <velocity>
     <exact>6.9</exact>
    </velocity>
   </state>
   <state>
    <position>
     <point>
      <x>125.044</x>
      <y>0.02</y>
     </point>
    </position>
    <orientation>
     <exact>-0.0</exact>
    </orientation>
    <time>
     <exact>127</exact>
    </time>
    <velocity>
     <exact>6.9</exact>
    </velocity>
   </state>
   <state>
    <position>
     <point>
      <x>125.734</x>
      <y>0.02</y>
     </point>
    </position>
    <orientation>
     <exact>-0.0</exact>
    </orientation>
    <time>
     <exact>128</exact>
    </time>
    <velocity>
     <exact>6.9</exact>
    </velocity>
   </state>
   <state>
    <position>
     <point>
      <x>126.424</x>
      <y>0.02</y>
     </point>
    </position>
    <orientation>
     <exact>-0.0</exact>
    </orientation>
    <time>
     <exact>129</exact>
    </time>
    <velocity>
     <exact>6.9</exact>
    </velocity>
   </state>
   <state>
    <position>
     <point>
      <x>127.114</x>
      <y>0.02</y>
     </point>
    </position>
    <orientation>
     <exact>-0.0</exact>
    </orientation>
    <time>
     <exact>130</exact>
    </time>
    <velocity>
     <exact>6.9</exact>
    </velocity>
   </state>
   <state>
    <position>
     <point>
      <x>127.804</x>
      <y>0.02</y>
     </point>
    </position>
    <orientation>
     <exact>-0.0</exact>
    </orientation>
    <time>
     <exact>131</exact>
    </time>
    <velocity>
     <exact>6.9</exact>
    </velocity>
   </state>
   <state>
    <position>
     <point>
      <x>128.494</x>
      <y>0.02</y>
     </point>
    </position>
    <orientation>
     <exact>-0.0</exact>
    </orientation>
    <time>
     <exact>132</exact>
    </time>
    <velocity>
     <exact>6.9</exact>
    </velocity>
   </state>
   <state>
    <position>
     <point>
      <x>129.184</x>
      <y>0.02</y>
     </point>
    </position>
    <orientation>
     <exact>-0.0</exact>
    </orientation>
    <time>
     <exact>133</exact>
    </time>
    <velocity>
     <exact>6.9</exact>
    </velocity>
   </state>
   <state>
    <position>
     <point>
      <x>129.874</x>
      <y>0.02</y>
     </point>
    </position>
    <orientation>
     <exact>-0.0</exact>
    </orientation>
    <time>
     <exact>134</exact>
    </time>
    <velocity>
     <exact>6.9</exact>
    </velocity>
   </state>
   <state>
    <position>
     <point>
      <x>130.564</x>
      <y>0.02</y>
     </point>
    </position>
    <orientation>
     <exact>-0.0</exact>
    </orientation>
    <time>
     <exact>135</exact>
    </time>
    <velocity>
     <exact>6.9</exact>
    </velocity>
   </state>
   <state>
    <position>
     <point>
      <x>131.254</x>
      <y>0.02</y>
     </point>
    </position>
    <orientation>
     <exact>-0.0</exact>
    </orientation>
    <time>
     <exact>136</exact>
    </time>
    <velocity>
     <exact>6.9</exact>
    </velocity>
   </state>
   <state>
    <position>
     <point>
      <x>131.944</x>
      <y>0.02</y>
     </point>
    </position>
    <orientation>
     <exact>-0.0</exact>
    </orientation>
    <time>
     <exact>137</exact>
    </time>
    <velocity>
     <exact>6.9</exact>
    </velocity>
   </state>
   <state>
    <position>
     <point>
      <x>132.634</x>
      <y>0.02</y>
     </point>
    </position>
    <orientation>
     <exact>-0.0</exact>
    </orientation>
    <time>
     <exact>138</exact>
    </time>
    <velocity>
     <exact>6.9</exact>
    </velocity>
   </state>
   <state>
    <position>
     <point>
      <x>133.324</x>
      <y>0.02</y>
     </point>
    </position>
    <orientation>
     <exact>-0.0</exact>
    </orientation>
    <time>
     <exact>139</exact>
    </time>
    <velocity>
     <exact>6.9</exact>
    </velocity>
   </state>
   <state>
    <position>
     <point>
      <x>134.014</x>
      <y>0.02</y>
     </point>
    </position>
    <orientation>
     <exact>-0.0</exact>
    </orientation>
    <time>
     <exact>140</exact>
    </time>
    <velocity>
     <exact>6.9</exact>
    </velocity>
   </state>
   <state>
    <position>
     <point>
      <x>134.704</x>
      <y>0.02</y>
     </point>
    </position>
    <orientation>
     <exact>-0.0</exact>
    </orientation>
    <time>
     <exact>141</exact>
    </time>
    <velocity>
     <exact>6.9</exact>
    </velocity>
   </state>
   <state>
    <position>
     <point>
      <x>135.394</x>
      <y>0.02</y>
     </point>
    </position>
    <orientation>
     <exact>-0.0</exact>
    </orientation>
    <time>
     <exact>142</exact>
    </time>
    <velocity>
     <exact>6.9</exact>
    </velocity>
   </state>
   <state>
    <position>
     <point>
      <x>136.084</x>
      <y>0.02</y>
     </point>
    </position>
    <orientation>
     <exact>-0.0</exact>
    </orientation>
    <time>
     <exact>143</exact>
    </time>
    <velocity>
     <exact>6.9</exact>
    </velocity>
   </state>
   <state>
    <position>
     <point>
      <x>136.774</x>
      <y>0.02</y>
     </point>
    </position>
    <orientation>
     <exact>-0.0</exact>
    </orientation>
    <time>
     <exact>144</exact>
    </time>
    <velocity>
     <exact>6.9</exact>
    </velocity>
   </state>
   <state>
    <position>
     <point>
      <x>137.464</x>
      <y>0.02</y>
     </point>
    </position>
    <orientation>
     <exact>-0.0</exact>
    </orientation>
    <time>
     <exact>145</exact>
    </time>
    <velocity>
     <exact>6.9</exact>
    </velocity>
   </state>
   <state>
    <position>
     <point>
      <x>138.154</x>
      <y>0.02</y>
     </point>
    </position>
    <orientation>
     <exact>-0.0</exact>
    </orientation>
    <time>
     <exact>146</exact>
    </time>
    <velocity>
     <exact>6.9</exact>
    </velocity>
   </state>
   <state>
    <position>
     <point>
      <x>138.844</x>
      <y>0.02</y>
     </point>
    </position>
    <orientation>
     <exact>-0.0</exact>
    </orientation>
    <time>
     <exact>147</exact>
    </time>
    <velocity>
     <exact>6.9</exact>
    </velocity>
   </state>
   <state>
    <position>
     <point>
      <x>139.534</x>
      <y>0.02</y>
     </point>
    </position>
    <orientation>
     <exact>-0.0</exact>
    </orientation>
    <time>
     <exact>148</exact>
    </time>
    <velocity>
     <exact>6.9</exact>
    </velocity>
   </state>
   <state>
    <position>
     <point>
      <x>140.224</x>
      <y>0.02</y>
     </point>
    </position>
    <orientation>
     <exact>-0.0</exact>
    </orientation>
    <time>
     <exact>149</exact>
    </time>
    <velocity>
     <exact>6.9</exact>
    </velocity>
   </state>
   <state>
    <position>
     <point>
      <x>140.914</x>
      <y>0.02</y>
     </point>
    </position>
    <orientation>
     <exact>-0.0</exact>
    </orientation>
    <time>
     <exact>150</exact>
    </time>
    <velocity>
     <exact>6.9</exact>
    </velocity>
   </state>
   <state>
    <position>
     <point>
      <x>141.604</x>
      <y>0.02</y>
     </point>
    </position>
    <orientation>
     <exact>-0.0</exact>
    </orientation>
    <time>
     <exact>151</exact>
    </time>
    <velocity>
     <exact>6.9</exact>
    </velocity>
   </state>
   <state>
    <position>
     <point>
      <x>142.294</x>
      <y>0.02</y>
     </point>
    </position>
    <orientation>
     <exact>-0.0</exact>
    </orientation>
    <time>
     <exact>152</exact>
    </time>
    <velocity>
     <exact>6.9</exact>
    </velocity>
   </state>
   <state>
    <position>
     <point>
      <x>142.984</x>
      <y>0.02</y>
     </point>
    </position>
    <orientation>
     <exact>-0.0</exact>
    </orientation>
    <time>
     <exact>153</exact>
    </time>
    <velocity>
     <exact>6.9</exact>
    </velocity>
   </state>
   <state>
    <position>
     <point>
      <x>143.674</x>
      <y>0.02</y>
     </point>
    </position>
    <orientation>
     <exact>-0.0</exact>
    </orientation>
    <time>
     <exact>154</exact>
    </time>
    <velocity>
     <exact>6.9</exact>
    </velocity>
   </state>
   <state>
    <position>
     <point>
      <x>144.364</x>
      <y>0.02</y>
     </point>
    </position>
    <orientation>
     <exact>-0.0</exact>
    </orientation>
    <time>
     <exact>155</exact>
    </time>
    <velocity>
     <exact>6.9</exact>
    </velocity>
   </state>
   <state>
    <position>
     <point>
      <x>145.054</x>
      <y>0.02</y>
     </point>
    </position>
    <orientation>
     <exact>-0.0</exact>
    </orientation>
    <time>
     <exact>156</exact>
    </time>
    <velocity>
     <exact>6.9</exact>
    </velocity>
   </state>
   <state>
    <position>
     <point>
      <x>145.744</x>
      <y>0.02</y>
     </point>
    </position>
    <orientation>
     <exact>-0.0</exact>
    </orientation>
    <time>
     <exact>157</exact>
    </time>
    <velocity>
     <exact>6.9</exact>
    </velocity>
   </state>
   <state>
    <position>
     <point>
      <x>146.434</x>
      <y>0.02</y>
     </point>
    </position>
    <orientation>
     <exact>-0.0</exact>
    </orientation>
    <time>
     <exact>158</exact>
    </time>
    <velocity>
     <exact>6.9</exact>
    </velocity>
   </state>
   <state>
    <position>
     <point>
      <x>147.124</x>
      <y>0.02</y>
     </point>
    </position>
    <orientation>
     <exact>-0.0</exact>
    </orientation>
    <time>
     <exact>159</exact>
    </time>
    <velocity>
     <exact>6.9</exact>
    </velocity>
   </state>
   <state>
    <position>
     <point>
      <x>147.814</x>
      <y>0.02</y>
     </point>
    </position>
    <orientation>
     <exact>-0.0</exact>
    </orientation>
    <time>
     <exact>160</exact>
    </time>
    <velocity>
     <exact>6.9</exact>
    </velocity>
   </state>
   <state>
    <position>
     <point>
      <x>148.504</x>
      <y>0.02</y>
     </point>
    </position>
    <orientation>
     <exact>-0.0</exact>
    </orientation>
    <time>
     <exact>161</exact>
    </time>
    <velocity>
     <exact>6.9</exact>
    </velocity>
   </state>
   <state>
    <position>
     <point>
      <x>149.194</x>
      <y>0.02</y>
     </point>
    </position>
    <orientation>
     <exact>-0.0</exact>
    </orientation>
    <time>
     <exact>162</exact>
    </time>
    <velocity>
     <exact>6.9</exact>
    </velocity>
   </state>
   <state>
    <position>
     <point>
      <x>149.884</x>
      <y>0.02</y>
     </point>
    </position>
    <orientation>
     <exact>-0.0</exact>
    </orientation>
    <time>
     <exact>163</exact>
    </time>
    <velocity>
     <exact>6.9</exact>
    </velocity>
   </state>
   <state>
    <position>
     <point>
      <x>150.574</x>
      <y>0.02</y>
     </point>
    </position>
    <orientation>
     <exact>-0.0</exact>
    </orientation>
    <time>
     <exact>164</exact>
    </time>
    <velocity>
     <exact>6.9</exact>
    </velocity>
   </state>
   <state>
    <position>
     <point>
      <x>151.264</x>
      <y>0.02</y>
     </point>
    </position>
    <orientation>
     <exact>-0.0</exact>
    </orientation>
    <time>
     <exact>165</exact>
    </time>
    <velocity>
     <exact>6.9</exact>
    </velocity>
   </state>
   <state>
    <position>
     <point>
      <x>151.954</x>
      <y>0.02</y>
     </point>
    </position>
    <orientation>
     <exact>-0.0</exact>
    </orientation>
    <time>
     <exact>166</exact>
    </time>
    <velocity>
     <exact>6.9</exact>
    </velocity>
   </state>
   <state>
    <position>
     <point>
      <x>152.644</x>
      <y>0.02</y>
     </point>
    </position>
    <orientation>
     <exact>-0.0</exact>
    </orientation>
    <time>
     <exact>167</exact>
    </time>
    <velocity>
     <exact>6.9</exact>
    </velocity>
   </state>
   <state>
    <position>
     <point>
      <x>153.334</x>
      <y>0.02</y>
     </point>
    </position>
    <orientation>
     <exact>-0.0</exact>
    </orientation>
    <time>
     <exact>168</exact>
    </time>
    <velocity>
     <exact>6.9</exact>
    </velocity>
   </state>
   <state>
    <position>
     <point>
      <x>154.024</x>
      <y>0.02</y>
     </point>
    </position>
    <orientation>
     <exact>-0.0</exact>
    </orientation>
    <time>
     <exact>169</exact>
    </time>
    <velocity>
     <exact>6.9</exact>
    </velocity>
   </state>
   <state>
    <position>
     <point>
      <x>154.714</x>
      <y>0.02</y>
     </point>
    </position>
    <orientation>
     <exact>-0.0</exact>
    </orientation>
    <time>
     <exact>170</exact>
    </time>
    <velocity>
     <exact>6.9</exact>
    </velocity>
   </state>
   <state>
    <position>
     <point>
      <x>155.404</x>
      <y>0.02</y>
     </point>
    </position>
    <orientation>
     <exact>-0.0</exact>
    </orientation>
    <time>
     <exact>171</exact>
    </time>
    <velocity>
     <exact>6.9</exact>
    </velocity>
   </state>
   <state>
    <position>
     <point>
      <x>156.094</x>
      <y>0.02</y>
     </point>
    </position>
    <orientation>
     <exact>-0.0</exact>
    </orientation>
    <time>
     <exact>172</exact>
    </time>
    <velocity>
     <exact>6.9</exact>
    </velocity>
   </state>
   <state>
    <position>
     <point>
      <x>156.784</x>
      <y>0.02</y>
     </point>
    </position>
    <orientation>
     <exact>-0.0</exact>
    </orientation>
    <time>
     <exact>173</exact>
    </time>
    <velocity>
     <exact>6.9</exact>
    </velocity>
   </state>
   <state>
    <position>
     <point>
      <x>157.474</x>
      <y>0.02</y>
     </point>
    </position>
    <orientation>
     <exact>-0.0</exact>
    </orientation>
    <time>
     <exact>174</exact>
    </time>
    <velocity>
     <exact>6.9</exact>
    </velocity>
   </state>
   <state>
    <position>
     <point>
      <x>158.164</x>
      <y>0.02</y>
     </point>
    </position>
    <orientation>
     <exact>-0.0</exact>
    </orientation>
    <time>
     <exact>175</exact>
    </time>
    <velocity>
     <exact>6.9</exact>
    </velocity>
   </state>
   <state>
    <position>
     <point>
      <x>158.854</x>
      <y>0.02</y>
     </point>
    </position>
    <orientation>
     <exact>-0.0</exact>
    </orientation>
    <time>
     <exact>176</exact>
    </time>
    <velocity>
     <exact>6.9</exact>
    </velocity>
   </state>
   <state>
    <position>
     <point>
      <x>159.544</x>
      <y>0.02</y>
     </point>
    </position>
    <orientation>
     <exact>-0.0</exact>
    </orientation>
    <time>
     <exact>177</exact>
    </time>
    <velocity>
     <exact>6.9</exact>
    </velocity>
   </state>
   <state>
    <position>
     <point>
      <x>160.234</x>
      <y>0.02</y>
     </point>
    </position>
    <orientation>
     <exact>-0.0</exact>
    </orientation>
    <time>
     <exact>178</exact>
    </time>
    <velocity>
     <exact>6.9</exact>
    </velocity>
   </state>
   <state>
    <position>
     <point>
      <x>160.924</x>
      <y>0.02</y>
     </point>
    </position>
    <orientation>
     <exact>-0.0</exact>
    </orientation>
    <time>
     <exact>179</exact>
    </time>
    <velocity>
     <exact>6.9</exact>
    </velocity>
   </state>
   <state>
    <position>
     <point>
      <x>161.614</x>
      <y>0.02</y>
     </point>
    </position>
    <orientation>
     <exact>-0.0</exact>
    </orientation>
    <time>
     <exact>180</exact>
    </time>
    <velocity>
     <exact>6.9</exact>
    </velocity>
   </state>
   <state>
    <position>
     <point>
      <x>162.304</x>
      <y>0.02</y>
     </point>
    </position>
    <orientation>
     <exact>-0.0</exact>
    </orientation>
    <time>
     <exact>181</exact>
    </time>
    <velocity>
     <exact>6.9</exact>
    </velocity>
   </state>
   <state>
    <position>
     <point>
      <x>162.994</x>
      <y>0.02</y>
     </point>
    </position>
    <orientation>
     <exact>-0.0</exact>
    </orientation>
    <time>
     <exact>182</exact>
    </time>
    <velocity>
     <exact>6.9</exact>
    </velocity>
   </state>
   <state>
    <position>
     <point>
      <x>163.684</x>
      <y>0.02</y>
     </point>
    </position>
    <orientation>
     <exact>-0.0</exact>
    </orientation>
    <time>
     <exact>183</exact>
    </time>
    <velocity>
     <exact>6.9</exact>
    </velocity>
   </state>
   <state>
    <position>
     <point>
      <x>164.374</x>
      <y>0.02</y>
     </point>
    </position>
    <orientation>
     <exact>-0.0</exact>
    </orientation>
    <time>
     <exact>184</exact>
    </time>
    <velocity>
     <exact>6.9</exact>
    </velocity>
   </state>
   <state>
    <position>
     <point>
      <x>165.064</x>
      <y>0.02</y>
     </point>
    </position>
    <orientation>
     <exact>-0.0</exact>
    </orientation>
    <time>
     <exact>185</exact>
    </time>
    <velocity>
     <exact>6.9</exact>
    </velocity>
   </state>
   <state>
    <position>
     <point>
      <x>165.754</x>
      <y>0.02</y>
     </point>
    </position>
    <orientation>
     <exact>-0.0</exact>
    </orientation>
    <time>
     <exact>186</exact>
    </time>
    <velocity>
     <exact>6.9</exact>
    </velocity>
   </state>
   <state>
    <position>
     <point>
      <x>166.444</x>
      <y>0.02</y>
     </point>
    </position>
    <orientation>
     <exact>-0.0</exact>
    </orientation>
    <time>
     <exact>187</exact>
    </time>
    <velocity>
     <exact>6.9</exact>
    </velocity>
   </state>
   <state>
    <position>
     <point>
      <x>167.134</x>
      <y>0.02</y>
     </point>
    </position>
    <orientation>
     <exact>-0.0</exact>
    </orientation>
    <time>
     <exact>188</exact>
    </time>
    <velocity>
     <exact>6.9</exact>
    </velocity>
   </state>
   <state>
    <position>
     <point>
      <x>167.824</x>
      <y>0.02</y>
     </point>
    </position>
    <orientation>
     <exact>-0.0</exact>
    </orientation>
    <time>
     <exact>189</exact>
    </time>
    <velocity>
     <exact>6.9</exact>
    </velocity>
   </state>
   <state>
    <position>
     <point>
      <x>168.514</x>
      <y>0.02</y>
     </point>
    </position>
    <orientation>
     <exact>-0.0</exact>
    </orientation>
    <time>
     <exact>190</exact>
    </time>
    <velocity>
     <exact>6.9</exact>
    </velocity>
   </state>
   <state>
    <position>
     <point>
      <x>169.204</x>
      <y>0.02</y>
     </point>
    </position>
    <orientation>
     <exact>-0.0</exact>
    </orientation>
    <time>
     <exact>191</exact>
    </time>
    <velocity>
     <exact>6.9</exact>
    </velocity>
   </state>
   <state>
    <position>
     <point>
      <x>169.894</x>
      <y>0.02</y>
     </point>
    </position>
    <orientation>
     <exact>-0.0</exact>
    </orientation>
    <time>
     <exact>192</exact>
    </time>
    <velocity>
     <exact>6.9</exact>
    </velocity>
   </state>
   <state>
    <position>
     <point>
      <x>170.584</x>
      <y>0.02</y>
     </point>
    </position>
    <orientation>
     <exact>-0.0</exact>
    </orientation>
    <time>
     <exact>193</exact>
    </time>
    <velocity>
     <exact>6.9</exact>
    </velocity>
   </state>
   <state>
    <position>
     <point>
      <x>171.274</x>
      <y>0.02</y>
     </point>
    </position>
    <orientation>
     <exact>-0.0</exact>
    </orientation>
    <time>
     <exact>194</exact>
    </time>
    <velocity>
     <exact>6.9</exact>
    </velocity>
   </state>
   <state>
    <position>
     <point>
      <x>171.964</x>
      <y>0.02</y>
     </point>
    </position>
    <orientation>
     <exact>-0.0</exact>
    </orientation>
    <time>
     <exact>195</exact>
    </time>
    <velocity>
     <exact>6.9</exact>
    </velocity>
   </state>
   <state>
    <position>
     <point>
      <x>172.654</x>
      <y>0.02</y>
     </point>
    </position>
    <orientation>
     <exact>-0.0</exact>
    </orientation>
    <time>
     <exact>196</exact>
    </time>
    <velocity>
     <exact>6.9</exact>
    </velocity>
   </state>
   <state>
    <position>
     <point>
      <x>173.344</x>
      <y>0.02</y>
     </point>
    </position>
    <orientation>
     <exact>-0.0</exact>
    </orientation>
    <time>
     <exact>197</exact>
    </time>
    <velocity>
     <exact>6.9</exact>
    </velocity>
   </state>
   <state>
    <position>
     <point>
      <x>174.034</x>
      <y>0.02</y>
     </point>
    </position>
    <orientation>
     <exact>-0.0</exact>
    </orientation>
    <time>
     <exact>198</exact>
    </time>
    <velocity>
     <exact>6.9</exact>
    </velocity>
   </state>
   <state>
    <position>
     <point>
      <x>174.724</x>
      <y>0.02</y>
     </point>
    </position>
    <orientation>
     <exact>-0.0</exact>
    </orientation>
    <time>
     <exact>199</exact>
    </time>
    <velocity>
     <exact>6.9</exact>
    </velocity>
   </state>
   <state>
    <position>
     <point>
      <x>175.414</x>
      <y>0.02</y>
     </point>
    </position>
    <orientation>
     <exact>-0.0</exact>
    </orientation>
    <time>
     <exact>200</exact>
    </time>
    <velocity>
     <exact>6.9</exact>
    </velocity>
   </state>
  </trajectory>
 </dynamicObstacle>
 <planningProblem id="900">
  <initialState>
   <position>
    <point>
     <x>0.0</x>
     <y>0.0</y>
    </point>
   </position>
   <velocity>
    <exact>8.0</exact>
   </velocity>
   <orientation>
    <exact>0.0</exact>
   </orientation>
   <yawRate>
    <exact>0.0</exact>
   </yawRate>
   <slipAngle>
    <exact>0.0</exact>
   </slipAngle>
   <time>
    <exact>0</exact>
   </time>
  </initialState>
  <goalState>
   <time>
    <intervalStart>0</intervalStart>
    <intervalEnd>200</intervalEnd>
   </time>
   <position>
    <rectangle>
     <length>20.0</length>
     <width>4.0</width>
     <orientation>0.0</orientation>
     <center>
      <x>400.0</x>
      <y>0.0</y>
     </center>
    </rectangle>
   </position>
   <velocity>
    <intervalStart>9.0</intervalStart>
    <intervalEnd>11.0</intervalEnd>
   </velocity>
  </goalState>
 </planningProblem>
</commonRoad>